scribdl/__init__.py
scribdl/authorize.py
scribdl/command_line.py
scribdl/const.py
scribdl/downloader.py
scribdl/exceptions.py
scribdl/internals.py
scribdl/pdf_converter.py
scribdl/version.py
scribdl/content/__init__.py
scribdl/content/audiobook.py
scribdl/content/base.py
scribdl/content/book.py
scribdl/content/document.py
scribdl/content/test/__init__.py
scribdl/content/test/test_audiobook.py
scribdl/content/test/test_base.py
scribdl/content/test/test_book.py
scribdl/content/test/test_document.py
scribdl/test/__init__.py
scribdl/test/test_command_line.py
scribdl/test/test_download.py
scribdl/test/test_internals.py
scribd_downloader-1.3.1.dist-info/METADATA
scribd_downloader-1.3.1.dist-info/WHEEL
scribd_downloader-1.3.1.dist-info/entry_points.txt
scribd_downloader-1.3.1.dist-info/top_level.txt
scribd_downloader-1.3.1.dist-info/RECORD
