Metadata-Version: 2.1
Name: scribd-downloader
Version: 1.3.1
Summary: Download documents, books and audiobooks off Scribd
Home-page: https://www.github.com/ritiek/scribd-downloader
Author: Ritiek Malhotra
Author-email: ritiekmalhotra123@gmail.com
License: MIT
Download-URL: https://github.com/ritiek/scribd-downloader/archive/v1.3.1.tar.gz
Keywords: scribd-downloader,documents,command-line,python
Platform: UNKNOWN
Requires-Dist: requests (>=2.19.1)
Requires-Dist: BeautifulSoup4 (>=4.6.3)
Requires-Dist: img2pdf (>=0.3.1)
Requires-Dist: md2pdf (>=0.4)
